matemux/__main__.py
matemux/cook.py
matemux/help.txt
matemux/parser.py
matemux/recipe.py
matemux/tmux.py
matemux-0.1.3.dist-info/entry_points.txt
matemux-0.1.3.dist-info/LICENSE
matemux-0.1.3.dist-info/WHEEL
matemux-0.1.3.dist-info/METADATA
matemux-0.1.3.dist-info/RECORD
