Metadata-Version: 2.1
Name: matemux
Version: 0.1.3
Summary: tmux session generator
Home-page: https://github.com/kamyabzad/matemux
License: MIT
Keywords: tmux,console,automation
Author: Kamyab Taghizadeh
Author-email: kamyab.zad@gmail.com
Requires-Python: >=3.6,<4.0
Classifier: License :: OSI Approved :: MIT License
Classifier: Programming Language :: Python :: 3
Classifier: Programming Language :: Python :: 3.6
Classifier: Programming Language :: Python :: 3.7
Classifier: Programming Language :: Python :: 3.8
Classifier: Programming Language :: Python :: 3.9
Requires-Dist: PyYAML (>=5.4.1,<6.0.0)
Project-URL: Repository, https://github.com/kamyabzad/matemux
